pinyin/__init__.py
pinyin/config.py
pinyin/utils.py
pinyin/data/term.dic
pinyin/data/user_dict.dic
pinyin/data/word.dic
pinyin/data/words.dic
smart_pinyin-0.5.1.dist-info/METADATA
smart_pinyin-0.5.1.dist-info/WHEEL
smart_pinyin-0.5.1.dist-info/top_level.txt
smart_pinyin-0.5.1.dist-info/RECORD
