Metadata-Version: 2.4
Name: smart_pinyin
Version: 0.5.1
Summary: Smart Chinese-to-Pinyin converter.
Author: mapix, Elephant Liu
License-Expression: MIT
Project-URL: Homepage, https://github.com/xospc/python-smart-pinyin
Classifier: Programming Language :: Python :: 3
Requires-Python: >=3.10
Requires-Dist: jieba
